auto_tag/__init__.py
auto_tag/__main__.py
auto_tag/cli.py
auto_tag/constants.py
auto_tag/core.py
auto_tag/detectors.py
auto_tag/detectors_config.py
auto_tag/entrypoint.py
auto_tag/exception.py
auto_tag/git_custom_env.py
auto_tag/tag_search_strategy.py
auto_tag-0.8.2.dist-info/LICENSE.md
auto_tag-0.8.2.dist-info/METADATA
auto_tag-0.8.2.dist-info/WHEEL
auto_tag-0.8.2.dist-info/entry_points.txt
auto_tag-0.8.2.dist-info/top_level.txt
auto_tag-0.8.2.dist-info/RECORD
